dimtim/__init__.py
dimtim/run.py
dimtim/helpers/__init__.py
dimtim/helpers/logger.py
dimtim/helpers/management/__init__.py
dimtim/helpers/management/command.py
dimtim/helpers/management/cron_command.py
dimtim/helpers/management/runner.py
dimtim/interfaces/__init__.py
dimtim/interfaces/serializable.py
dimtim/utils/__init__.py
dimtim/utils/buffer.py
dimtim/utils/debug.py
dimtim/utils/decorators.py
dimtim/utils/duration.py
dimtim/utils/environ.py
dimtim/utils/hashing.py
dimtim/utils/importing.py
dimtim/utils/itertools.py
dimtim/utils/json.py
dimtim/utils/path.py
dimtim/utils/proxy.py
dimtim/utils/random.py
dimtim/utils/terminal.py
dimtim/utils/text.py
dimtim/utils/timezone.py
dimtim/utils/data/__init__.py
dimtim/utils/data/wordlists.py
dimtim_utils-0.1.14.dist-info/METADATA
dimtim_utils-0.1.14.dist-info/WHEEL
dimtim_utils-0.1.14.dist-info/entry_points.txt
dimtim_utils-0.1.14.dist-info/top_level.txt
dimtim_utils-0.1.14.dist-info/RECORD
