Metadata-Version: 2.4
Name: dimtim-utils
Version: 0.1.14
Summary: "Dim-Tim, Inc." python utils
Author-email: "Dim-Tim, Inc." <info@dim-tim.com>
Maintainer-email: Bobsans <mr.bobsans@gmail.com>
License-Expression: MIT
Project-URL: Repository, https://github.com/dim-tim-inc/dimtim-utils
Keywords: utils,debug,decorator,json,proxy,random,terminal,timezone
Classifier: Development Status :: 5 - Production/Stable
Classifier: Intended Audience :: Developers
Classifier: Operating System :: OS Independent
Classifier: Programming Language :: Python
Classifier: Programming Language :: Python :: 3
Classifier: Programming Language :: Python :: 3.10
Classifier: Programming Language :: Python :: 3.11
Classifier: Programming Language :: Python :: 3.12
Classifier: Programming Language :: Python :: 3.13
Classifier: Programming Language :: Python :: 3.14
Classifier: Topic :: Software Development
Classifier: Topic :: Software Development :: Libraries
Requires-Python: >=3.10
Requires-Dist: asgiref>=3.5.2
Requires-Dist: frozendict>=2.3.4
Requires-Dist: tzdata>=2023.3
Provides-Extra: full
Requires-Dist: beautifulsoup4; extra == "full"
Requires-Dist: markdown; extra == "full"
Requires-Dist: pydantic; extra == "full"
Requires-Dist: tzdata; extra == "full"
